<?xml version="1.0" encoding="UTF-8"?><Script duration="76321" iterationNum="1" name="HCM_ManageGradeRates_CreateduplicateGradeRates_0051.xlsx" reportTime="8/05/2020 01:24:00 AM" responseTime="0" result="Passed" testDate="8/05/2020 01:22:41 AM" type="basic.step" workspace="Global HR(Admn)"><i18nProperty duration="Playback Time (sec)" name="Page" recid="Record ID" result="Result" summary="Summary" type="Type"/><Initialize duration="3491" name="Initialize Total (sec)" responseTime="0" result="Passed" summary="" type="basic.init"><Step duration="2826" name="Launch Browser: InternetExplorer 11.959.18362.0" responseTime="0" result="Passed" summary="" type="basic.step"/></Initialize><Run duration="65079" name="Iteration Total (sec)" responseTime="0" result="Passed" summary="" type="basic.iteration"><Step duration="2" name="Info" responseTime="0" result="Passed" summary="Comments: Legislative Input For Search is : SA Legislative Data Group" type="basic.comment"/><Step duration="0" name="Info" responseTime="0" result="Passed" summary="Comments: Effective Start Date is : 7/2/20" type="basic.comment"/><Step duration="0" name="Info" responseTime="0" result="Passed" summary="Comments: Grade Name is : Leg8" type="basic.comment"/><Step duration="0" name="Info" responseTime="0" result="Passed" summary="Comments: Grade code is : Leg8" type="basic.comment"/><Step duration="0" name="Info" responseTime="0" result="Passed" summary="Comments: Grade MIN Value is : 10" type="basic.comment"/><Step duration="0" name="Info" responseTime="0" result="Passed" summary="Comments: Grade MAX Value is : 20" type="basic.comment"/><Step duration="0" name="Info" responseTime="0" result="Passed" summary="Comments: Grade Value is : 11" type="basic.comment"/><Step duration="87" name="Navigate https://ejop-test.login.em2.oraclecloud.com/oam/server/obrareq.cgi?encquery%3DUwPZv10x5U%2B3mIubEg4moKZjBGxOwfdPv2LxXjj91AZXE2IKvjWlw4PZN7hFmdTG%2BIK3mLxNDVQcHOUeIHbxIV%2FGW62UEUF7w%2BcOks6YUPO%2Banxcs7awvdnZSbGln%2BV0cB37%2BKn6OoFs846LQbMIZr..." recid="8" responseTime="0" result="Passed" summary="" type="ft.action"/><Step duration="3912" name="WaitForPage https://ejop-test.login.em2.oraclecloud.com/oam/server/obrareq.cgi?encquery%3DUwPZv10x5U%2B3mIubEg4moKZjBGxOwfdPv2LxXjj91AZXE2IKvjWlw4PZN7hFmdTG%2BIK3mLxNDVQcHOUeIHbxIV%2FGW62UEUF7w%2BcOks6YUPO%2Banxcs7awvdnZSbGln%2BV0cB37%2BKn6OoFs846LQbM..." recid="10" responseTime="0" result="Passed" summary="" type="web.pageComplete"/><Step duration="217" name="SetText textBox(&quot;@id='userid'&quot;) Sujit.swain" recid="11" responseTime="0" result="Passed" summary="" type="ft.action"/><Step duration="113" name="PressTab textBox(&quot;@id='userid'&quot;)" recid="12" responseTime="0" result="Passed" summary="" type="ft.action"/><Step duration="38" name="SetPassword textBox(&quot;@id='password'&quot;) ******" recid="13" responseTime="0" result="Passed" summary="" type="ft.action"/><Step duration="45" name="PressEnter textBox(&quot;@id='password'&quot;)" responseTime="0" result="Passed" summary="" type="ft.action"/><Step duration="3046" name="Think: 3.019 (sec)." responseTime="0" result="Passed" summary="" type="basic.comment"/><Step duration="319" name="Click link(&quot;@text='You have a new home page!'&quot;)" responseTime="0" result="Passed" summary="" type="ft.action"/><Step duration="100" name="DoubleClick link(&quot;@text='You have a new home page!'&quot;)" responseTime="0" result="Passed" summary="" type="ft.action"/><StepGroup duration="2578" name="WaitForPage https://ejop-test.fa.em2.oraclecloud.com/fscmUI/faces/FuseWelcome?_afrLoop=5277087201047796&amp;_afrWindowMode=0&amp;_afrWindowId=null&amp;_adf.ctrl-state=aenbdfgww_1&amp;_afrFS=16&amp;_afrMT=screen&amp;_afrMFW=1920&amp;_afrMFH=878&amp;_afrMFDW=1920&amp;_afrMFDH=1080&amp;_afrMFC..." recid="18" responseTime="0" result="Passed" summary="" type="web.pageComplete"><Step duration="0" name="Frame (URL=https://ejop-test.fa.em2.oraclecloud.com/fscmUI/afr/blank.html)" responseTime="0" result="Passed" summary="" type="web.frame"/></StepGroup><Step duration="282" name="Click link(&quot;@text='My Client Groups'&quot;)" recid="4" responseTime="0" result="Passed" summary="" type="ft.action"/><Step duration="1048" name="Think: 1.018 (sec)." responseTime="0" result="Passed" summary="" type="basic.comment"/><Step duration="154" name="Click link(&quot;@text='Workforce Structures'&quot;)" responseTime="0" result="Passed" summary="" type="ft.action"/><StepGroup duration="800" name="WaitForPage https://ejop-test.fa.em2.oraclecloud.com/fscmUI/faces/FuseWelcome?_afrLoop=5277087201047796&amp;_afrWindowMode=0&amp;_afrWindowId=null&amp;_adf.ctrl-state=aenbdfgww_1&amp;_afrFS=16&amp;_afrMT=screen&amp;_afrMFW=1920&amp;_afrMFH=878&amp;_afrMFDW=1920&amp;_afrMFDH=1080&amp;_afrMFC..." responseTime="0" result="Passed" summary="" type="web.pageComplete"><Step duration="0" name="Frame (URL=https://ejop-test.fa.em2.oraclecloud.com/fscmUI/afr/blank.html)" responseTime="0" result="Passed" summary="" type="web.frame"/></StepGroup><Step duration="1044" name="Think: 1.018 (sec)." responseTime="0" result="Passed" summary="" type="basic.comment"/><Step duration="5548" name="focus" responseTime="0" result="Passed" summary="" type="ft.action"/><Step duration="46" name="Think: 0.026 (sec)." responseTime="0" result="Passed" summary="" type="basic.comment"/><Step duration="1479" name="focus" recid="10" responseTime="0" result="Passed" summary="" type="ft.action"/><Step duration="1661" name="Think: 1.639 (sec)." responseTime="0" result="Passed" summary="" type="basic.comment"/><Step duration="1290" name="focus" recid="11" responseTime="0" result="Passed" summary="" type="ft.action"/><Step duration="1764" name="Think: 1.731 (sec)." responseTime="0" result="Passed" summary="" type="basic.comment"/><Step duration="2923" name="Click link(&quot;@id='_FOpt1:_FOr1:0:_FOSritemNode_workforce_management_workforce_structures:0:_FOTsr1:0:ll01Upl:UPsp1:ll01Pce:ll01Itr:3:ll02Pce:ll01Lv:0:ll01Pse:ll01Cl'&quot;)" recid="12" responseTime="0" result="Passed" summary="" type="ft.action"/><Step duration="2340" name="DoubleClick link(&quot;@id='_FOpt1:_FOr1:0:_FOSritemNode_workforce_management_workforce_structures:0:_FOTsr1:0:ll01Upl:UPsp1:ll01Pce:ll01Itr:3:ll02Pce:ll01Lv:0:ll01Pse:ll01Cl'&quot;)" recid="12" responseTime="0" result="Passed" summary="" type="ft.action"/><Step duration="1373" name="Think: 1.341 (sec)." responseTime="0" result="Passed" summary="" type="basic.comment"/><Step duration="395" name="Click element(&quot;@text='Create'&quot;)" responseTime="0" result="Passed" summary="" type="ft.action"/><Step duration="1372" name="Think: 1.34 (sec)." responseTime="0" result="Passed" summary="" type="basic.comment"/><Step duration="248" name="Click textBox(&quot;@id='_FOpt1:_FOr1:0:_FOSritemNode_workforce_management_workforce_structures:0:MAnt2:1:AP4:AT5:legislativeDataGroupNameId::content'&quot;)" responseTime="0" result="Passed" summary="" type="ft.action"/><Step duration="126" name="Click link(&quot;@id='_FOpt1:_FOr1:0:_FOSritemNode_workforce_management_workforce_structures:0:MAnt2:1:AP4:AT5:legislativeDataGroupNameId::lovIconId'&quot;)" responseTime="0" result="Passed" summary="" type="ft.action"/><Step duration="1522" name="Think: 1.494 (sec)." responseTime="0" result="Passed" summary="" type="basic.comment"/><Step duration="123" name="Click link(&quot;@text='Search...'&quot;)" recid="16" responseTime="0" result="Passed" summary="" type="ft.action"/><Step duration="925" name="Think: 0.894 (sec)." responseTime="0" result="Passed" summary="" type="basic.comment"/><Step duration="137" name="Click textBox(&quot;@id='_FOpt1:_FOr1:0:_FOSritemNode_workforce_management_workforce_structures:0:MAnt2:1:AP4:AT5:legislativeDataGroupNameId::_afrLovInternalQueryId:value00::content'&quot;)" responseTime="0" result="Passed" summary="" type="ft.action"/><Step duration="82" name="SetText textBox(&quot;@id='_FOpt1:_FOr1:0:_FOSritemNode_workforce_management_workforce_structures:0:MAnt2:1:AP4:AT5:legislativeDataGroupNameId::_afrLovInternalQueryId:value00::content'&quot;) SA Legislative Data Group" responseTime="0" result="Passed" summary="" type="ft.action"/><Step duration="189" name="Click button(&quot;@id='_FOpt1:_FOr1:0:_FOSritemNode_workforce_management_workforce_structures:0:MAnt2:1:AP4:AT5:legislativeDataGroupNameId::_afrLovInternalQueryId::search'&quot;)" responseTime="0" result="Passed" summary="" type="ft.action"/><Step duration="1376" name="Think: 1.349 (sec)." responseTime="0" result="Passed" summary="" type="basic.comment"/><Step duration="349" name="Click element(&quot;@text='SA Legislative Data Group'&quot;)" responseTime="0" result="Passed" summary="" type="ft.action"/><Step duration="1891" name="Think: 1.864 (sec)." responseTime="0" result="Passed" summary="" type="basic.comment"/><Step duration="131" name="Click button(&quot;@id='_FOpt1:_FOr1:0:_FOSritemNode_workforce_management_workforce_structures:0:MAnt2:1:AP4:AT5:legislativeDataGroupNameId::lovDialogId::ok'&quot;)" responseTime="0" result="Passed" summary="" type="ft.action"/><Step duration="1302" name="Think: 1.277 (sec)." responseTime="0" result="Passed" summary="" type="basic.comment"/><Step duration="132" name="Click button(&quot;@id='_FOpt1:_FOr1:0:_FOSritemNode_workforce_management_workforce_structures:0:MAnt2:1:AP4:AT5:commandButton2'&quot;)" responseTime="0" result="Passed" summary="" type="ft.action"/><Step duration="2815" name="Think: 2.782 (sec)." responseTime="0" result="Passed" summary="" type="basic.comment"/><Step duration="149" name="Click textBox(&quot;@id='_FOpt1:_FOr1:0:_FOSritemNode_workforce_management_workforce_structures:0:MAnt2:2:AP2:esd::content'&quot;)" responseTime="0" result="Passed" summary="" type="ft.action"/><Step duration="73" name="SetText textBox(&quot;@id='_FOpt1:_FOr1:0:_FOSritemNode_workforce_management_workforce_structures:0:MAnt2:2:AP2:esd::content'&quot;) 7/2/20" responseTime="0" result="Passed" summary="" type="ft.action"/><Step duration="809" name="Think: 0.782 (sec)." responseTime="0" result="Passed" summary="" type="basic.comment"/><Step duration="174" name="Click textBox(&quot;@id='_FOpt1:_FOr1:0:_FOSritemNode_workforce_management_workforce_structures:0:MAnt2:2:AP2:inputText2::content'&quot;)" responseTime="0" result="Passed" summary="" type="ft.action"/><Step duration="72" name="SetText textBox(&quot;@id='_FOpt1:_FOr1:0:_FOSritemNode_workforce_management_workforce_structures:0:MAnt2:2:AP2:inputText2::content'&quot;) Leg8" responseTime="0" result="Passed" summary="" type="ft.action"/><Step duration="112" name="Click link(&quot;@id='_FOpt1:_FOr1:0:_FOSritemNode_workforce_management_workforce_structures:0:MAnt2:2:AP2:selectOneChoice1::drop'&quot;)" responseTime="0" result="Passed" summary="" type="ft.action"/><Step duration="124" name="Think: 0.096 (sec)." responseTime="0" result="Passed" summary="" type="basic.comment"/><Step duration="888" name="Click element(&quot;@text='Salary'&quot;)" responseTime="0" result="Passed" summary="" type="ft.action"/><Step duration="630" name="Think: 0.604 (sec)." responseTime="0" result="Passed" summary="" type="basic.comment"/><Step duration="153" name="Click link(&quot;@id='_FOpt1:_FOr1:0:_FOSritemNode_workforce_management_workforce_structures:0:MAnt2:2:AP2:selectOneChoice2::drop'&quot;)" responseTime="0" result="Passed" summary="" type="ft.action"/><Step duration="106" name="Click element(&quot;@text='Active'&quot;)" responseTime="0" result="Passed" summary="" type="ft.action"/><Step duration="752" name="Think: 0.729 (sec)." responseTime="0" result="Passed" summary="" type="basic.comment"/><Step duration="108" name="Click link(&quot;@id='_FOpt1:_FOr1:0:_FOSritemNode_workforce_management_workforce_structures:0:MAnt2:2:AP2:rateFrequency::drop'&quot;)" responseTime="0" result="Passed" summary="" type="ft.action"/><Step duration="716" name="Think: 0.692 (sec)." responseTime="0" result="Passed" summary="" type="basic.comment"/><Step duration="95" name="Click element(&quot;@text='Annually'&quot;)" responseTime="0" result="Passed" summary="" type="ft.action"/><Step duration="1499" name="Think: 1.478 (sec)." responseTime="0" result="Passed" summary="" type="basic.comment"/><Step duration="405" name="Click element(&quot;@text='m'&quot;)" responseTime="0" result="Passed" summary="" type="ft.action"/><Step duration="1440" name="Think: 1.414 (sec)." responseTime="0" result="Passed" summary="" type="basic.comment"/><Step duration="144" name="Click textBox(&quot;@id='_FOpt1:_FOr1:0:_FOSritemNode_workforce_management_workforce_structures:0:MAnt2:2:AP2:inputText2::content'&quot;)" responseTime="0" result="Passed" summary="" type="ft.action"/><Step duration="1444" name="Think: 1.414 (sec)." responseTime="0" result="Passed" summary="" type="basic.comment"/><StepGroup duration="530" name="CapturePage https://ejop-test.fa.em2.oraclecloud.com/hcmUI/faces/FndOverview?fnd=%3B%3B%3B%3Bfalse%3B256%3B%3B%3B&amp;fndGlobalItemNodeId=itemNode_workforce_management_workforce_structures&amp;_afrLoop=5277097145884981&amp;_afrWindowMode=0&amp;_afrWindowId=148qi3as3g..." recid="27" responseTime="0" result="Passed" summary="" type="web.capPage"><Step duration="0" name="Frame (URL=https://ejop-test.fa.em2.oraclecloud.com/hcmUI/afr/blank.html)" responseTime="0" result="Passed" summary="" type="web.frame"/></StepGroup></Run><Finish duration="7244" name="Finish Total (sec)" responseTime="0" result="Passed" summary="" type="basic.finish"><Step duration="383" name="Click element(&quot;@id='pt1:_UIScmil1u::icon'&quot;)" responseTime="0" result="Passed" summary="" type="ft.action"/><Step duration="2127" name="Think: 2.094 (sec)." responseTime="0" result="Passed" summary="" type="basic.comment"/><Step duration="116" name="Click link(&quot;@text='Sign Out'&quot;)" recid="21" responseTime="0" result="Passed" summary="" type="ft.action"/><Step duration="3743" name="WaitForPage https://ejop-test.login.em2.oraclecloud.com/fusion_apps/pages/logoutConsent.jsp?logout_done_url=https%3A%2F%2Fejop-test.fa.em2.oraclecloud.com%3A443%2FfscmUI%2FadfAuthentication%3F_adf.authenticate%3Dtrue&amp;logoutId=E0829D2B5100C99AEE5D15F6F..." recid="22" responseTime="0" result="Passed" summary="" type="web.pageComplete"/><Step duration="434" name="WaitForPage https://ejop-test.login.em2.oraclecloud.com/fusion_apps/pages/logoutConsent.jsp?logout_done_url=https%3A%2F%2Fejop-test.fa.em2.oraclecloud.com%3A443%2FfscmUI%2FadfAuthentication%3F_adf.authenticate%3Dtrue&amp;logoutId=E0829D2B5100C99AEE5D15F6F..." recid="24" responseTime="0" result="Passed" summary="" type="web.pageComplete"/><Step duration="8" name="closeBrowser" recid="27" responseTime="0" result="Passed" summary="" type="ft.action"/></Finish></Script>